heiwa4126/hello/__about__.py
heiwa4126/hello/__init__.py
heiwa4126/hello/cli.py
heiwa4126/hello/hello.py
heiwa4126_hello-0.0.8.dist-info/METADATA
heiwa4126_hello-0.0.8.dist-info/WHEEL
heiwa4126_hello-0.0.8.dist-info/entry_points.txt
heiwa4126_hello-0.0.8.dist-info/licenses/LICENSE
heiwa4126_hello-0.0.8.dist-info/RECORD
