Metadata-Version: 2.3
Name: heiwa4126.hello
Version: 0.0.8
Summary: A simple hello function.
Project-URL: Repository, https://github.com/heiwa4126/pip-heiwa4126-hello.git
Project-URL: Homepage, https://github.com/heiwa4126/pip-heiwa4126-hello#readme
Project-URL: Issues, https://github.com/heiwa4126/pip-heiwa4126-hello/issues
Author-email: heiwa4126 <heiwa4126@gmail.com>
License-Expression: MIT
License-File: LICENSE
Keywords: demo,hello
Classifier: License :: OSI Approved :: MIT License
Classifier: Operating System :: OS Independent
Classifier: Programming Language :: Python
Classifier: Programming Language :: Python :: 3.8
Classifier: Programming Language :: Python :: 3.9
Classifier: Programming Language :: Python :: 3.10
Classifier: Programming Language :: Python :: 3.11
Classifier: Programming Language :: Python :: 3.12
Classifier: Programming Language :: Python :: Implementation :: CPython
Requires-Python: >=3.8
